dj_pony/tenant/__init__.py
dj_pony/tenant/admin.py
dj_pony/tenant/apps.py
dj_pony/tenant/auth_backends.py
dj_pony/tenant/constants.py
dj_pony/tenant/context_processor.py
dj_pony/tenant/drf/__init__.py
dj_pony/tenant/drf/permissions.py
dj_pony/tenant/drf/serializers.py
dj_pony/tenant/exceptions.py
dj_pony/tenant/helpers/__init__.py
dj_pony/tenant/helpers/tenant_extra_data.py
dj_pony/tenant/helpers/tenant_json_field.py
dj_pony/tenant/helpers/tenant_relationships.py
dj_pony/tenant/helpers/tenant_settings.py
dj_pony/tenant/helpers/tenants.py
dj_pony/tenant/management/__init__.py
dj_pony/tenant/management/commands/__init__.py
dj_pony/tenant/management/commands/create_tenant.py
dj_pony/tenant/management/commands/createtenant.py
dj_pony/tenant/managers.py
dj_pony/tenant/middleware.py
dj_pony/tenant/migrations/0001_initial.py
dj_pony/tenant/migrations/__init__.py
dj_pony/tenant/mixins.py
dj_pony/tenant/models.py
dj_pony/tenant/polymorphic/__init__.py
dj_pony/tenant/polymorphic/base_models.py
dj_pony/tenant/polymorphic/managers.py
dj_pony/tenant/polymorphic/models.py
dj_pony/tenant/retrievers/__init__.py
dj_pony/tenant/retrievers/ulid.py
dj_pony/tenant/settings.py
dj_pony/tenant/tenant_retrievers.py
dj_pony/tenant/tools/__init__.py
dj_pony/tenant/tools/context_managers.py
dj_pony/tenant/urls.py
dj_pony/tenant/utils.py
dj_pony/tenant/validators.py
dj_pony/tenant/views.py
licensezero.json
dj_pony.tenant-0.10.2.dist-info/LICENSE
dj_pony.tenant-0.10.2.dist-info/WHEEL
dj_pony.tenant-0.10.2.dist-info/METADATA
dj_pony.tenant-0.10.2.dist-info/RECORD
